XStatic_TWikiDraw_moin-2004.10.23.2-py3.13-nspkg.pth
xstatic/pkg/twikidraw_moin/__init__.py
xstatic/pkg/twikidraw_moin/__init__.py~
xstatic/pkg/twikidraw_moin/data/twikidraw_moin.jar
xstatic_twikidraw_moin-2004.10.23.2.dist-info/METADATA
xstatic_twikidraw_moin-2004.10.23.2.dist-info/WHEEL
xstatic_twikidraw_moin-2004.10.23.2.dist-info/namespace_packages.txt
xstatic_twikidraw_moin-2004.10.23.2.dist-info/top_level.txt
xstatic_twikidraw_moin-2004.10.23.2.dist-info/RECORD
