Metadata-Version: 2.4
Name: XStatic-TWikiDraw-moin
Version: 2004.10.23.2
Summary: TWikiDraw-moin 2004.10.23 (XStatic packaging standard)
Home-page: http://moinmo.in/OliverGraf/TWikiDrawPlugin
Maintainer: Reimar Bauer
Maintainer-email: rb.proj@googlemail.com
License: (same as TWikiDraw-moin)
Keywords: twikidraw_moin xstatic
Platform: any
Dynamic: description
Dynamic: home-page
Dynamic: keywords
Dynamic: license
Dynamic: maintainer
Dynamic: maintainer-email
Dynamic: platform
Dynamic: summary
